Metadata-Version: 2.4
Name: pymongo-aggregate
Version: 0.0.3
Summary: MongoDB aggregate operations declared for python
Author-email: Giorgio Ripani <g.ripani93@gmail.com>
License-Expression: MIT
Project-URL: Homepage, https://github.com/gripani/PyMongoAggregate/tree/main
Classifier: Programming Language :: Python :: 3
Classifier: Operating System :: OS Independent
Requires-Python: >=3.12
License-File: LICENSE.txt
Dynamic: license-file
